antropy/__init__.py
antropy/entropy.py
antropy/fractal.py
antropy/utils.py
antropy-0.1.8.dist-info/LICENSE
antropy-0.1.8.dist-info/METADATA
antropy-0.1.8.dist-info/WHEEL
antropy-0.1.8.dist-info/top_level.txt
antropy-0.1.8.dist-info/RECORD
