Metadata-Version: 2.1
Name: antropy
Version: 0.1.8
Summary: AntroPy: entropy and complexity of time-series in Python
Author-email: Raphael Vallat <raphaelvallat9@gmail.com>
Maintainer-email: Raphael Vallat <raphaelvallat9@gmail.com>
License: BSD (3-clause)
Project-URL: Homepage, https://github.com/raphaelvallat/antropy/
Project-URL: Downloads, https://github.com/raphaelvallat/antropy/
Classifier: Intended Audience :: Science/Research
Classifier: Operating System :: MacOS
Classifier: Operating System :: POSIX
Classifier: Operating System :: Unix
Classifier: Programming Language :: Python :: 3.9
Classifier: Programming Language :: Python :: 3.10
Classifier: Programming Language :: Python :: 3.11
Classifier: Programming Language :: Python :: 3.12
Classifier: Topic :: Scientific/Engineering :: Mathematics
Requires-Python: >=3.9
License-File: LICENSE
Requires-Dist: numpy
Requires-Dist: scipy
Requires-Dist: scikit-learn
Requires-Dist: numba>=0.57
Requires-Dist: stochastic
Provides-Extra: test
Requires-Dist: pytest>=6; extra == "test"
Requires-Dist: pytest-cov; extra == "test"
Requires-Dist: coverage[toml]>=5.3; extra == "test"
Requires-Dist: ruff; extra == "test"
Provides-Extra: docs
Requires-Dist: sphinx>7.0.0; extra == "docs"
Requires-Dist: numpydoc; extra == "docs"
Requires-Dist: sphinx-copybutton; extra == "docs"
Requires-Dist: sphinx-design; extra == "docs"
